icing/__init__.py
icing/config.py
icing/inference.py
icing/learner.py
icing/similarity_.py
icing/align/__init__.py
icing/align/setup.py
icing/align/test_speedup_c_alignment.py
icing/core/__init__.py
icing/core/analyse_results.py
icing/core/cloning.py
icing/core/cluster.py
icing/core/distances.py
icing/core/learning_function.py
icing/core/parallel_distance.py
icing/core/similarity_scores.py
icing/externals/DbCore.py
icing/externals/Tango.py
icing/externals/__init__.py
icing/externals/_sparse_affinity_propagation.py
icing/externals/neighbors.py
icing/externals/sparse_affinity_propagation.py
icing/externals/spectral.py
icing/kernel/__init__.py
icing/models/__init__.py
icing/models/model.py
icing/parallel/__init__.py
icing/parallel/setup.py
icing/parallel/test_speedup_c_alignment.py
icing/plotting/__init__.py
icing/plotting/silhouette.py
icing/utils/__init__.py
icing/utils/extra.py
icing/utils/io.py
icing/validation/__init__.py
icing/validation/scores.py
icing-0.1.4.data/scripts/ici_analysis.py
icing-0.1.4.data/scripts/ici_run.py
icing-0.1.4.dist-info/DESCRIPTION.rst
icing-0.1.4.dist-info/METADATA
icing-0.1.4.dist-info/RECORD
icing-0.1.4.dist-info/WHEEL
icing-0.1.4.dist-info/metadata.json
icing-0.1.4.dist-info/top_level.txt
