Metadata-Version: 2.0
Name: icing
Version: 0.1.4
Summary: A package to clonal relate immunoglobulins
Home-page: https://github.com/slipguru/icing
Author: Federico Tomasi
Author-email: federico.tomasi@dibris.unige.it
License: FreeBSD
Download-URL: https://github.com/slipguru/icing/archive/0.1.4.tar.gz
Keywords: IG,immunoglobulins,clonotypes
Platform: UNKNOWN
Classifier: Development Status :: 4 - Beta
Classifier: Environment :: Console
Classifier: Intended Audience :: Science/Research
Classifier: Intended Audience :: Developers
Classifier: Programming Language :: Python
Classifier: License :: OSI Approved :: BSD License
Classifier: Topic :: Software Development
Classifier: Topic :: Scientific/Engineering :: Bio-Informatics
Classifier: Operating System :: POSIX
Classifier: Operating System :: Unix
Classifier: Operating System :: MacOS
Requires: numpy (>=1.10.1)
Requires: scipy (>=0.16.1)
Requires: sklearn (>=0.17)
Requires: matplotlib (>=1.5.1)
Requires: seaborn (>=0.7.0)
